hashin_shtrikman_mp/__init__.py
hashin_shtrikman_mp/core/__init__.py
hashin_shtrikman_mp/core/match_finder.py
hashin_shtrikman_mp/core/temp_mp_contribs_utils.py
hashin_shtrikman_mp/core/utilities.py
hashin_shtrikman_mp/core/genetic_algorithm/__init__.py
hashin_shtrikman_mp/core/genetic_algorithm/genetic_algorithm.py
hashin_shtrikman_mp/core/genetic_algorithm/genetic_algorithm_parameters.py
hashin_shtrikman_mp/core/genetic_algorithm/genetic_algorithm_result.py
hashin_shtrikman_mp/core/genetic_algorithm/member.py
hashin_shtrikman_mp/core/genetic_algorithm/optimization_params.py
hashin_shtrikman_mp/core/genetic_algorithm/population.py
hashin_shtrikman_mp/core/user_input/__init__.py
hashin_shtrikman_mp/core/user_input/aggregate.py
hashin_shtrikman_mp/core/user_input/material.py
hashin_shtrikman_mp/core/user_input/material_property.py
hashin_shtrikman_mp/core/user_input/mixture.py
hashin_shtrikman_mp/core/user_input/mixture_property.py
hashin_shtrikman_mp/core/user_input/user_input.py
hashin_shtrikman_mp/core/visualization/__init__.py
hashin_shtrikman_mp/core/visualization/composite_property_plotter.py
hashin_shtrikman_mp/core/visualization/optimization_result_visualizer.py
hashin_shtrikman_mp/io/__init__.py
hashin_shtrikman_mp/io/inputs/__init__.py
hashin_shtrikman_mp/io/inputs/data/cost_calculation_formulas.yaml
hashin_shtrikman_mp/io/inputs/data/display_table_headers.yaml
hashin_shtrikman_mp/io/inputs/data/mp_property_docs.yaml
hashin_shtrikman_mp/io/outputs/__init__.py
hashin_shtrikman_mp/log/__init__.py
hashin_shtrikman_mp/log/custom_logger.py
hashin_shtrikman_mp-0.1.2.dist-info/licenses/LICENSE
hashin_shtrikman_mp-0.1.2.dist-info/METADATA
hashin_shtrikman_mp-0.1.2.dist-info/WHEEL
hashin_shtrikman_mp-0.1.2.dist-info/top_level.txt
hashin_shtrikman_mp-0.1.2.dist-info/RECORD
