Metadata-Version: 2.4
Name: hashin_shtrikman_mp
Version: 0.1.2
Summary: Determine the optimal material properties and volume fractions for each component of an n-phase mixture to meet a set of desired composite material properties.
Project-URL: repository, https://github.com/carlacupcake/hashin_shtrikman_mp
Project-URL: changelog, https://github.com/carlacupcake/hashin_shtrikman_mp/.chglog/CHANGELOG.tpl.md
Requires-Python: >=3.9
License-File: LICENSE
Requires-Dist: emmet-core>=0.74.5
Requires-Dist: matplotlib-stubs>=0.2.0
Requires-Dist: monty>=2023.11.3
Requires-Dist: mp-api>=0.39.1
Requires-Dist: mpi4py>=3.1.5
Requires-Dist: mpcontribs-client>=5.10.0
Requires-Dist: nbformat>=4.2.0
Requires-Dist: numpy>=1.26.2
Requires-Dist: pandas>=2.2.0
Requires-Dist: pydantic>=2.5.0
Requires-Dist: pydantic-core>=2.14.1
Requires-Dist: pydantic-settings>=2.1.0
Requires-Dist: pytest>=8.3.4
Provides-Extra: tests
Requires-Dist: pytest; extra == "tests"
Provides-Extra: docs
Requires-Dist: jupyter_contrib_nbextensions>=0.7.0; extra == "docs"
Requires-Dist: notebook==6.4.12; extra == "docs"
Requires-Dist: mkdocs>=1.4.0; extra == "docs"
Requires-Dist: mkdocs-autorefs>=0.4.1; extra == "docs"
Requires-Dist: mkdocs-jupyter>=0.24.6; extra == "docs"
Requires-Dist: mkdocs-section-index>=0.3.4; extra == "docs"
Requires-Dist: mkdocstrings>=0.19.0; extra == "docs"
Requires-Dist: mkdocstrings-python>=0.7.1; extra == "docs"
Requires-Dist: pymdown-extensions>=9.6; extra == "docs"
Provides-Extra: dev
Requires-Dist: ruff>=0.4.10; extra == "dev"
Requires-Dist: isort; extra == "dev"
Dynamic: license-file
